{
  "id": "MAP_ROUTE13VOLCANO1",
  "name": "Route13Volcano1",
  "layout": "LAYOUT_ROUTE13VOLCANO1",
  "music": "MUS_ROUTE3",
  "region_map_section": "MAPSEC_ROUTE_13",
  "requires_flash": false,
  "weather": "WEATHER_VOLCANIC_ASH",
  "map_type": "MAP_TYPE_NONE",
  "allow_cycling": true,
  "allow_escaping": false,
  "allow_running": true,
  "show_map_name": true,
  "floor_number": 0,
  "battle_scene": "MAP_BATTLE_SCENE_NORMAL",
  "connections": [
    {
      "map": "MAP_ROUTE13",
      "offset": -26,
      "direction": "left"
    }
  ],
  "object_events": [
    {
      "type": "object",
      "graphics_id": "OBJ_EVENT_GFX_CABLE_CLUB_RECEPTIONIST",
      "x": 24,
      "y": 55,
      "elevation": 0,
      "movement_type": "MOVEMENT_TYPE_NONE",
      "movement_range_x": 0,
      "movement_range_y": 0,
      "trainer_type": "TRAINER_TYPE_NONE",
      "trainer_sight_or_berry_tree_id": "0",
      "script": "HotSpringGirl",
      "flag": "0"
    },
    {
      "type": "object",
      "graphics_id": "OBJ_EVENT_GFX_YOUNGSTER",
      "x": 1,
      "y": 46,
      "elevation": 0,
      "movement_type": "MOVEMENT_TYPE_FACE_UP",
      "movement_range_x": 0,
      "movement_range_y": 0,
      "trainer_type": "TRAINER_TYPE_NORMAL",
      "trainer_sight_or_berry_tree_id": "6",
      "script": "TRAINER_Volcano_Youngster",
      "flag": "FLAG_TEMP_1"
    },
    {
      "type": "object",
      "graphics_id": "OBJ_EVENT_GFX_LASS",
      "x": 8,
      "y": 12,
      "elevation": 0,
      "movement_type": "MOVEMENT_TYPE_FACE_LEFT",
      "movement_range_x": 0,
      "movement_range_y": 0,
      "trainer_type": "TRAINER_TYPE_NORMAL",
      "trainer_sight_or_berry_tree_id": "5",
      "script": "TRAINER_Volcano_Lass",
      "flag": "0"
    },
    {
      "type": "object",
      "graphics_id": "OBJ_EVENT_GFX_COOLTRAINER_M",
      "x": 33,
      "y": 43,
      "elevation": 0,
      "movement_type": "MOVEMENT_TYPE_FACE_RIGHT",
      "movement_range_x": 0,
      "movement_range_y": 0,
      "trainer_type": "TRAINER_TYPE_NORMAL",
      "trainer_sight_or_berry_tree_id": "6",
      "script": "TRAINER_Volcano_Trainer1",
      "flag": "0"
    },
    {
      "type": "object",
      "graphics_id": "OBJ_EVENT_GFX_BIKER",
      "x": 3,
      "y": 32,
      "elevation": 0,
      "movement_type": "MOVEMENT_TYPE_FACE_RIGHT",
      "movement_range_x": 0,
      "movement_range_y": 0,
      "trainer_type": "TRAINER_TYPE_NORMAL",
      "trainer_sight_or_berry_tree_id": "3",
      "script": "TRAINER_Volcano_BallTony1",
      "flag": "0"
    },
    {
      "type": "object",
      "graphics_id": "OBJ_EVENT_GFX_SWIMMER_F_LAND",
      "x": 29,
      "y": 50,
      "elevation": 0,
      "movement_type": "MOVEMENT_TYPE_LOOK_AROUND",
      "movement_range_x": 0,
      "movement_range_y": 0,
      "trainer_type": "TRAINER_TYPE_NONE",
      "trainer_sight_or_berry_tree_id": "0",
      "script": "NULL",
      "flag": "0"
    },
    {
      "type": "object",
      "graphics_id": "OBJ_EVENT_GFX_COOLTRAINER_F",
      "x": 58,
      "y": 71,
      "elevation": 0,
      "movement_type": "MOVEMENT_TYPE_FACE_RIGHT",
      "movement_range_x": 0,
      "movement_range_y": 0,
      "trainer_type": "TRAINER_TYPE_NORMAL",
      "trainer_sight_or_berry_tree_id": "8",
      "script": "Volcano_Aanah",
      "flag": "0"
    },
    {
      "type": "object",
      "graphics_id": "OBJ_EVENT_GFX_ITEM_BALL",
      "x": 44,
      "y": 19,
      "elevation": 0,
      "movement_type": "MOVEMENT_TYPE_NONE",
      "movement_range_x": 0,
      "movement_range_y": 0,
      "trainer_type": "TRAINER_TYPE_NONE",
      "trainer_sight_or_berry_tree_id": "0",
      "script": "volcanofirestone1",
      "flag": "FLAG_0x301"
    },
    {
      "type": "object",
      "graphics_id": "OBJ_EVENT_GFX_COOLTRAINER_M",
      "x": 20,
      "y": 34,
      "elevation": 0,
      "movement_type": "MOVEMENT_TYPE_NONE",
      "movement_range_x": 0,
      "movement_range_y": 0,
      "trainer_type": "TRAINER_TYPE_NORMAL",
      "trainer_sight_or_berry_tree_id": "5",
      "script": "Volcano_Skidmore",
      "flag": "0"
    },
    {
      "type": "object",
      "graphics_id": "OBJ_EVENT_GFX_HIKER",
      "x": 40,
      "y": 81,
      "elevation": 0,
      "movement_type": "MOVEMENT_TYPE_NONE",
      "movement_range_x": 0,
      "movement_range_y": 0,
      "trainer_type": "TRAINER_TYPE_NORMAL",
      "trainer_sight_or_berry_tree_id": "5",
      "script": "Volcano_hiker1",
      "flag": "0"
    },
    {
      "type": "object",
      "graphics_id": "OBJ_EVENT_GFX_ITEM_BALL",
      "x": 1,
      "y": 48,
      "elevation": 0,
      "movement_type": "MOVEMENT_TYPE_NONE",
      "movement_range_x": 0,
      "movement_range_y": 0,
      "trainer_type": "TRAINER_TYPE_NONE",
      "trainer_sight_or_berry_tree_id": "0",
      "script": "volcanoultraball",
      "flag": "FLAG_0x300"
    },
    {
      "type": "object",
      "graphics_id": "OBJ_EVENT_GFX_ITEM_BALL",
      "x": 41,
      "y": 58,
      "elevation": 0,
      "movement_type": "MOVEMENT_TYPE_NONE",
      "movement_range_x": 0,
      "movement_range_y": 0,
      "trainer_type": "TRAINER_TYPE_NONE",
      "trainer_sight_or_berry_tree_id": "0",
      "script": "volcanomoonstone1",
      "flag": "FLAG_0x302"
    },
    {
      "type": "object",
      "graphics_id": "OBJ_EVENT_GFX_HIKER",
      "x": 31,
      "y": 37,
      "elevation": 0,
      "movement_type": "MOVEMENT_TYPE_FACE_RIGHT",
      "movement_range_x": 0,
      "movement_range_y": 0,
      "trainer_type": "TRAINER_TYPE_NORMAL",
      "trainer_sight_or_berry_tree_id": "6",
      "script": "Volcano_hiker2",
      "flag": "0"
    },
    {
      "type": "object",
      "graphics_id": "OBJ_EVENT_GFX_HIKER",
      "x": 7,
      "y": 47,
      "elevation": 0,
      "movement_type": "MOVEMENT_TYPE_FACE_RIGHT",
      "movement_range_x": 0,
      "movement_range_y": 0,
      "trainer_type": "TRAINER_TYPE_NORMAL",
      "trainer_sight_or_berry_tree_id": "10",
      "script": "Volcano_hiker3",
      "flag": "0"
    },
    {
      "type": "object",
      "graphics_id": "OBJ_EVENT_GFX_HIKER",
      "x": 42,
      "y": 74,
      "elevation": 0,
      "movement_type": "MOVEMENT_TYPE_NONE",
      "movement_range_x": 0,
      "movement_range_y": 0,
      "trainer_type": "TRAINER_TYPE_NORMAL",
      "trainer_sight_or_berry_tree_id": "6",
      "script": "Volcano_hiker4",
      "flag": "0"
    }
  ],
  "warp_events": [
    {
      "x": 27,
      "y": 60,
      "elevation": 0,
      "dest_map": "MAP_PALLET_TOWN",
      "dest_warp_id": "12"
    },
    {
      "x": 53,
      "y": 51,
      "elevation": 0,
      "dest_map": "MAP_ROUTE13VOLCANO2",
      "dest_warp_id": "0"
    },
    {
      "x": 21,
      "y": 54,
      "elevation": 0,
      "dest_map": "MAP_PEWTER_CITY_HOUSE2",
      "dest_warp_id": "0"
    }
  ],
  "coord_events": [
    {
      "type": "trigger",
      "x": 30,
      "y": 52,
      "elevation": 0,
      "var": "VAR_TEMP_1",
      "var_value": "0",
      "script": "OneIsland_KindleRoad_EmberSpa_EventScript_SpaHeal"
    },
    {
      "type": "trigger",
      "x": 29,
      "y": 52,
      "elevation": 0,
      "var": "VAR_TEMP_1",
      "var_value": "0",
      "script": "OneIsland_KindleRoad_EmberSpa_EventScript_SpaHeal"
    },
    {
      "type": "trigger",
      "x": 31,
      "y": 52,
      "elevation": 0,
      "var": "VAR_TEMP_1",
      "var_value": "0",
      "script": "OneIsland_KindleRoad_EmberSpa_EventScript_SpaHeal"
    },
    {
      "type": "trigger",
      "x": 28,
      "y": 52,
      "elevation": 0,
      "var": "VAR_TEMP_1",
      "var_value": "0",
      "script": "OneIsland_KindleRoad_EmberSpa_EventScript_SpaHeal"
    },
    {
      "type": "trigger",
      "x": 54,
      "y": 61,
      "elevation": 0,
      "var": "VAR_TEMP_1",
      "var_value": "0",
      "script": "OneIsland_KindleRoad_EmberSpa_EventScript_SpaHeal"
    },
    {
      "type": "trigger",
      "x": 53,
      "y": 61,
      "elevation": 0,
      "var": "VAR_TEMP_1",
      "var_value": "0",
      "script": "OneIsland_KindleRoad_EmberSpa_EventScript_SpaHeal"
    }
  ],
  "bg_events": [
    {
      "type": "sign",
      "x": 5,
      "y": 7,
      "elevation": 0,
      "player_facing_dir": "BG_EVENT_PLAYER_FACING_ANY",
      "script": "VolcanoSign"
    }
  ]
}
